dependencmake/__init__.py
dependencmake/__main__.py
dependencmake/cmake.py
dependencmake/config.py
dependencmake/dependency.py
dependencmake/dependency_list.py
dependencmake/exceptions.py
dependencmake/filesystem.py
dependencmake/resources/__init__.py
dependencmake/resources/dependencmake.yaml
dependencmake/version.py
dependencmake-0.1.0.dist-info/entry_points.txt
dependencmake-0.1.0.dist-info/LICENSE
dependencmake-0.1.0.dist-info/WHEEL
dependencmake-0.1.0.dist-info/METADATA
dependencmake-0.1.0.dist-info/RECORD
