Metadata-Version: 2.1
Name: dependencmake
Version: 0.1.0
Summary: Dependencies manager for projects using CMake
Home-page: https://github.com/pzehner/dependencmake
License: MIT
Author: Paul Zehner
Author-email: paul.zehner@alumni.enseeiht.fr
Requires-Python: >=3.6.1,<4.0.0
Classifier: Environment :: Console
Classifier: Intended Audience :: Developers
Classifier: License :: OSI Approved :: MIT License
Classifier: Operating System :: OS Independent
Classifier: Programming Language :: Python
Classifier: Programming Language :: Python :: 3
Classifier: Programming Language :: Python :: 3.6
Classifier: Programming Language :: Python :: 3.7
Classifier: Programming Language :: Python :: 3.8
Classifier: Programming Language :: Python :: 3.9
Requires-Dist: GitPython (>=3.1.13,<4.0.0)
Requires-Dist: PyYAML (>=5.4.1,<6.0.0)
Requires-Dist: dataclasses (>=0.8,<0.9); python_version >= "3.6" and python_version < "3.7"
Requires-Dist: furl (>=2.1.0,<3.0.0)
Requires-Dist: importlib-resources (>=5.1.0,<6.0.0); python_version < "3.7"
Requires-Dist: packaging (>=21.0,<22.0)
Requires-Dist: path (>=15.1.0,<16.0.0)
Requires-Dist: tqdm (>=4.56.2,<5.0.0)
Project-URL: Bug tracker, https://github.com/pzehner/dependencmake/issues
Project-URL: Repository, https://github.com/pzehner/dependencmake
